{
  "capturedAt": "2026-01-13T06:20:24.675Z",
  "geo": "US",
  "source": "google",
  "items": [
    {
      "keyword": "moussa diabaté",
      "articles": []
    },
    {
      "keyword": "emilia clarke",
      "articles": []
    },
    {
      "keyword": "gael monfils",
      "articles": []
    },
    {
      "keyword": "shabana azeez",
      "articles": []
    },
    {
      "keyword": "japan airlines",
      "articles": []
    },
    {
      "keyword": "jordan miller",
      "articles": []
    },
    {
      "keyword": "havana syndrome",
      "articles": []
    },
    {
      "keyword": "dylan cardwell",
      "articles": []
    },
    {
      "keyword": "lori harvey",
      "articles": []
    },
    {
      "keyword": "clippers",
      "articles": []
    }
  ]
}
