{
  "capturedAt": "2026-02-07T23:19:59.830Z",
  "geo": "JP",
  "source": "google",
  "items": [
    {
      "keyword": "平野歩夢",
      "articles": []
    },
    {
      "keyword": "加藤登紀子",
      "articles": []
    },
    {
      "keyword": "maga",
      "articles": []
    },
    {
      "keyword": "モノレール",
      "articles": []
    },
    {
      "keyword": "山梨 天気",
      "articles": []
    },
    {
      "keyword": "近鉄電車",
      "articles": []
    },
    {
      "keyword": "福井県",
      "articles": []
    },
    {
      "keyword": "ナント 対 リヨン",
      "articles": []
    },
    {
      "keyword": "延岡西日本マラソン",
      "articles": []
    },
    {
      "keyword": "衆院選 2026",
      "articles": []
    }
  ]
}
