{
  "capturedAt": "2026-04-26T09:44:12.466Z",
  "geo": "US",
  "source": "google",
  "items": [
    {
      "keyword": "coco gauff",
      "articles": []
    },
    {
      "keyword": "csk vs gt",
      "articles": []
    },
    {
      "keyword": "jiri lehecka",
      "articles": []
    },
    {
      "keyword": "long island",
      "articles": []
    },
    {
      "keyword": "taylor swift travis kelce",
      "articles": []
    },
    {
      "keyword": "sapphire princess cruise ship",
      "articles": []
    },
    {
      "keyword": "taylor swift",
      "articles": []
    },
    {
      "keyword": "future",
      "articles": []
    },
    {
      "keyword": "hail",
      "articles": []
    },
    {
      "keyword": "michael jackson cause of death",
      "articles": []
    }
  ]
}
