{
  "capturedAt": "2026-04-23T15:23:25.884Z",
  "geo": "US",
  "source": "google",
  "items": [
    {
      "keyword": "is reddit down",
      "articles": []
    },
    {
      "keyword": "iren stock",
      "articles": []
    },
    {
      "keyword": "maha",
      "articles": []
    },
    {
      "keyword": "jlr vehicle safety recall",
      "articles": []
    },
    {
      "keyword": "ty simpson",
      "articles": []
    },
    {
      "keyword": "james pearce jr",
      "articles": []
    },
    {
      "keyword": "ann li",
      "articles": []
    },
    {
      "keyword": "smh stock",
      "articles": []
    },
    {
      "keyword": "michael tilson thomas",
      "articles": []
    },
    {
      "keyword": "crm stock",
      "articles": []
    }
  ]
}
