{
  "capturedAt": "2026-05-10T17:28:12.765Z",
  "geo": "KR",
  "source": "google",
  "items": [
    {
      "keyword": "아스날",
      "articles": []
    },
    {
      "keyword": "아스널",
      "articles": []
    },
    {
      "keyword": "고소",
      "articles": []
    },
    {
      "keyword": "west ham đấu với arsenal",
      "articles": []
    },
    {
      "keyword": "뉴캐슬",
      "articles": []
    },
    {
      "keyword": "west ham vs arsenal",
      "articles": []
    },
    {
      "keyword": "웨스트 햄 대 아스널",
      "articles": []
    },
    {
      "keyword": "mi vs rcb",
      "articles": []
    },
    {
      "keyword": "과천시",
      "articles": []
    },
    {
      "keyword": "벙커버스터",
      "articles": []
    }
  ]
}
