{
  "capturedAt": "2026-03-30T04:21:34.354Z",
  "geo": "KR",
  "source": "google",
  "items": [
    {
      "keyword": "독도",
      "articles": []
    },
    {
      "keyword": "청와대",
      "articles": []
    },
    {
      "keyword": "신정훈",
      "articles": []
    },
    {
      "keyword": "황석희",
      "articles": []
    },
    {
      "keyword": "kospi",
      "articles": []
    },
    {
      "keyword": "오버워치 넥슨",
      "articles": []
    },
    {
      "keyword": "우리로",
      "articles": []
    },
    {
      "keyword": "나상도",
      "articles": []
    },
    {
      "keyword": "코스피",
      "articles": []
    },
    {
      "keyword": "김양",
      "articles": []
    }
  ]
}
