{
  "capturedAt": "2026-01-17T17:38:15.155Z",
  "geo": "US",
  "source": "google",
  "items": [
    {
      "keyword": "st andrews",
      "articles": []
    },
    {
      "keyword": "cayden lee",
      "articles": []
    },
    {
      "keyword": "lec",
      "articles": []
    },
    {
      "keyword": "wild vs sabres",
      "articles": []
    },
    {
      "keyword": "india u-19 vs bangladesh u-19",
      "articles": []
    },
    {
      "keyword": "georgia tech vs nc state",
      "articles": []
    },
    {
      "keyword": "galatasaray",
      "articles": []
    },
    {
      "keyword": "epl scores",
      "articles": []
    },
    {
      "keyword": "minnesota vs illinois",
      "articles": []
    },
    {
      "keyword": "uconn vs georgetown",
      "articles": []
    }
  ]
}
