{
  "capturedAt": "2026-03-15T20:17:40.603Z",
  "geo": "JP",
  "source": "google",
  "items": [
    {
      "keyword": "トランプ大統領",
      "articles": []
    },
    {
      "keyword": "ラツィオ 対 ミラン",
      "articles": []
    },
    {
      "keyword": "鹿児島地震",
      "articles": []
    },
    {
      "keyword": "鳴海唯",
      "articles": []
    },
    {
      "keyword": "コモ 対 ローマ",
      "articles": []
    },
    {
      "keyword": "la liga",
      "articles": []
    },
    {
      "keyword": "スバル レガシィ アウトバック",
      "articles": []
    },
    {
      "keyword": "spacex launch schedule",
      "articles": []
    },
    {
      "keyword": "紀平梨花",
      "articles": []
    },
    {
      "keyword": "ブルーノ・フェルナンデス",
      "articles": []
    }
  ]
}
