{
  "capturedAt": "2026-07-20T04:35:47.731Z",
  "geo": "US",
  "source": "google",
  "items": [
    {
      "keyword": "sandy brondello comment",
      "articles": []
    },
    {
      "keyword": "europe",
      "articles": []
    },
    {
      "keyword": "google play services",
      "articles": []
    },
    {
      "keyword": "legionnaires disease",
      "articles": []
    },
    {
      "keyword": "ralph sampson",
      "articles": []
    },
    {
      "keyword": "yaxel lendeborg",
      "articles": []
    },
    {
      "keyword": "cedric coward",
      "articles": []
    },
    {
      "keyword": "how many episodes in house of the dragon season 3",
      "articles": []
    },
    {
      "keyword": "david bednar",
      "articles": []
    },
    {
      "keyword": "taylor swift wedding invitation security",
      "articles": []
    }
  ]
}
