{
  "capturedAt": "2025-12-25T16:14:54.198Z",
  "geo": "JP",
  "source": "google",
  "items": [
    {
      "keyword": "snow storm warning",
      "articles": []
    },
    {
      "keyword": "ウォニョン",
      "articles": []
    },
    {
      "keyword": "内田有紀",
      "articles": []
    },
    {
      "keyword": "プラレール",
      "articles": []
    },
    {
      "keyword": "岸井ゆきの",
      "articles": []
    },
    {
      "keyword": "田辺桃子",
      "articles": []
    },
    {
      "keyword": "時東ぁみ",
      "articles": []
    },
    {
      "keyword": "fc東京",
      "articles": []
    },
    {
      "keyword": "ストレンジャーシングス 一番くじ",
      "articles": []
    },
    {
      "keyword": "磯村勇斗",
      "articles": []
    }
  ]
}
