{
  "capturedAt": "2026-04-05T19:10:01.863Z",
  "geo": "JP",
  "source": "google",
  "items": [
    {
      "keyword": "レンジャーズ 対 レッズ",
      "articles": []
    },
    {
      "keyword": "今日のドジャースの試合",
      "articles": []
    },
    {
      "keyword": "住宅ローン 変動金利",
      "articles": []
    },
    {
      "keyword": "インテル 対 ローマ",
      "articles": []
    },
    {
      "keyword": "かつや",
      "articles": []
    },
    {
      "keyword": "ドジャース 試合",
      "articles": []
    },
    {
      "keyword": "ロサンゼルス・ドジャース",
      "articles": []
    },
    {
      "keyword": "ahamo",
      "articles": []
    },
    {
      "keyword": "平野紫耀",
      "articles": []
    },
    {
      "keyword": "パク・ミニョン",
      "articles": []
    }
  ]
}
