{
  "capturedAt": "2026-01-20T12:28:06.864Z",
  "geo": "JP",
  "source": "google",
  "items": [
    {
      "keyword": "井上真央",
      "articles": []
    },
    {
      "keyword": "浜辺美波",
      "articles": []
    },
    {
      "keyword": "河内大和",
      "articles": []
    },
    {
      "keyword": "三田寛子",
      "articles": []
    },
    {
      "keyword": "pd",
      "articles": []
    },
    {
      "keyword": "ハウスm21",
      "articles": []
    },
    {
      "keyword": "瀬戸 康史",
      "articles": []
    },
    {
      "keyword": "荒木琉偉",
      "articles": []
    },
    {
      "keyword": "東京pd",
      "articles": []
    },
    {
      "keyword": "市原吏音",
      "articles": []
    }
  ]
}
