{
  "capturedAt": "2026-01-15T10:46:58.113Z",
  "geo": "JP",
  "source": "google",
  "items": [
    {
      "keyword": "ゆず",
      "articles": []
    },
    {
      "keyword": "レミオロメン",
      "articles": []
    },
    {
      "keyword": "西川貴教",
      "articles": []
    },
    {
      "keyword": "槇原敬之",
      "articles": []
    },
    {
      "keyword": "高橋文哉",
      "articles": []
    },
    {
      "keyword": "摘発",
      "articles": []
    },
    {
      "keyword": "若手俳優",
      "articles": []
    },
    {
      "keyword": "globe",
      "articles": []
    },
    {
      "keyword": "進撃の巨人 映画",
      "articles": []
    },
    {
      "keyword": "朝日奈央",
      "articles": []
    }
  ]
}
