{
  "capturedAt": "2026-01-16T14:15:35.080Z",
  "geo": "KR",
  "source": "google",
  "items": [
    {
      "keyword": "오늘부터 인간입니다만",
      "articles": []
    },
    {
      "keyword": "t1 한화",
      "articles": []
    },
    {
      "keyword": "거상",
      "articles": []
    },
    {
      "keyword": "u23",
      "articles": []
    },
    {
      "keyword": "전태풍",
      "articles": []
    },
    {
      "keyword": "손태진",
      "articles": []
    },
    {
      "keyword": "u-23 nhật bản đấu với u-23 jordan",
      "articles": []
    },
    {
      "keyword": "lck 컵",
      "articles": []
    },
    {
      "keyword": "일본 u-23 대 요르단 u-23",
      "articles": []
    },
    {
      "keyword": "okx",
      "articles": []
    }
  ]
}
