{
  "capturedAt": "2026-06-18T02:51:53.740Z",
  "geo": "US",
  "source": "google",
  "items": [
    {
      "keyword": "fifa president",
      "articles": []
    },
    {
      "keyword": "uga baseball game today",
      "articles": []
    },
    {
      "keyword": "juan cuadrado",
      "articles": []
    },
    {
      "keyword": "trae young trade",
      "articles": []
    },
    {
      "keyword": "jhon duran",
      "articles": []
    },
    {
      "keyword": "turkmenistan",
      "articles": []
    },
    {
      "keyword": "tornado watch vs warning",
      "articles": []
    },
    {
      "keyword": "immigration detention",
      "articles": []
    },
    {
      "keyword": "gol caracol en vivo",
      "articles": []
    },
    {
      "keyword": "estadio banorte",
      "articles": []
    }
  ]
}
