{
  "capturedAt": "2026-07-12T09:42:22.484Z",
  "geo": "JP",
  "source": "google",
  "items": [
    {
      "keyword": "大野智 タトゥー",
      "articles": []
    },
    {
      "keyword": "棚橋弘至",
      "articles": []
    },
    {
      "keyword": "dena 対 巨人",
      "articles": []
    },
    {
      "keyword": "フランス",
      "articles": []
    },
    {
      "keyword": "オスナ",
      "articles": []
    },
    {
      "keyword": "tシャツが乾くまで 相関図",
      "articles": []
    },
    {
      "keyword": "ヒグマ",
      "articles": []
    },
    {
      "keyword": "エンカーナシオン",
      "articles": []
    },
    {
      "keyword": "報道特集",
      "articles": []
    },
    {
      "keyword": "都市 対抗 野球 2026 北 関東 予選",
      "articles": []
    }
  ]
}
