{
  "capturedAt": "2026-04-07T19:50:25.913Z",
  "geo": "JP",
  "source": "google",
  "items": [
    {
      "keyword": "sporting vs arsenal",
      "score": 100
    },
    {
      "keyword": "吉野家",
      "score": 99
    },
    {
      "keyword": "皇室",
      "score": 98
    },
    {
      "keyword": "演技",
      "score": 97
    },
    {
      "keyword": "鎌倉パスタ パン食べ放題",
      "score": 96
    },
    {
      "keyword": "相撲",
      "score": 95
    },
    {
      "keyword": "abema",
      "score": 94
    },
    {
      "keyword": "ワークマン",
      "score": 93
    },
    {
      "keyword": "マスターズ 2026",
      "score": 92
    },
    {
      "keyword": "real madrid vs bayern",
      "score": 91
    }
  ]
}
