{
  "capturedAt": "2025-12-16T21:12:21.544Z",
  "geo": "US",
  "source": "youtube",
  "items": [
    {
      "keyword": "trailer",
      "score": 89.924
    },
    {
      "keyword": "avengers",
      "score": 45.224
    },
    {
      "keyword": "doomsday",
      "score": 45.224
    },
    {
      "keyword": "in",
      "score": 32.879
    },
    {
      "keyword": "me",
      "score": 29.081
    },
    {
      "keyword": "teaser",
      "score": 29.002
    },
    {
      "keyword": "things",
      "score": 26.303
    },
    {
      "keyword": "to",
      "score": 25.95
    },
    {
      "keyword": "lyrics",
      "score": 25.14
    },
    {
      "keyword": "season",
      "score": 23.982
    },
    {
      "keyword": "stranger",
      "score": 20.045
    },
    {
      "keyword": "volume",
      "score": 20.045
    },
    {
      "keyword": "is",
      "score": 19.281
    },
    {
      "keyword": "breakdown",
      "score": 18.823
    },
    {
      "keyword": "ñi",
      "score": 17.595
    },
    {
      "keyword": "sea",
      "score": 14.969
    },
    {
      "keyword": "minecraft",
      "score": 14.964
    },
    {
      "keyword": "game",
      "score": 14.049
    },
    {
      "keyword": "robert",
      "score": 13.824
    },
    {
      "keyword": "downey",
      "score": 13.824
    }
  ]
}
