{
  "capturedAt": "2026-02-22T23:45:53.084Z",
  "geo": "KR",
  "source": "google",
  "items": [
    {
      "keyword": "전한길",
      "score": 100
    },
    {
      "keyword": "엘 멘초",
      "score": 99
    },
    {
      "keyword": "모텔살인사건 신상",
      "score": 98
    },
    {
      "keyword": "뉴스",
      "score": 97
    },
    {
      "keyword": "พยากรณ์อากาศ",
      "score": 96
    },
    {
      "keyword": "barcelona đấu với levante",
      "score": 95
    },
    {
      "keyword": "south africa national cricket team vs india national cricket team standings",
      "score": 94
    },
    {
      "keyword": "mlb",
      "score": 93
    },
    {
      "keyword": "tottenham đấu với arsenal",
      "score": 92
    },
    {
      "keyword": "신혜선",
      "score": 91
    }
  ]
}
