{
  "capturedAt": "2026-02-05T09:34:17.825Z",
  "geo": "KR",
  "source": "google",
  "items": [
    {
      "keyword": "김혜수",
      "score": 100
    },
    {
      "keyword": "손아섭",
      "score": 99
    },
    {
      "keyword": "벤제마",
      "score": 98
    },
    {
      "keyword": "nep vs can",
      "score": 97
    },
    {
      "keyword": "메이플",
      "score": 96
    },
    {
      "keyword": "zimbabwe vs oman",
      "score": 95
    },
    {
      "keyword": "메이플스토리",
      "score": 94
    },
    {
      "keyword": "비트마인",
      "score": 93
    },
    {
      "keyword": "강남구청장",
      "score": 92
    },
    {
      "keyword": "한대음",
      "score": 91
    }
  ]
}
