{
  "capturedAt": "2026-02-15T16:53:51.560Z",
  "geo": "US",
  "source": "google",
  "items": [
    {
      "keyword": "levante - valencia c. f.",
      "score": 100
    },
    {
      "keyword": "levante vs valencia",
      "score": 99
    },
    {
      "keyword": "netherlands",
      "score": 98
    },
    {
      "keyword": "torino vs bologna",
      "score": 97
    },
    {
      "keyword": "jake paul",
      "score": 96
    },
    {
      "keyword": "who is jake paul",
      "score": 95
    },
    {
      "keyword": "tpe country",
      "score": 94
    },
    {
      "keyword": "shaheen afridi",
      "score": 93
    },
    {
      "keyword": "utah basketball",
      "score": 92
    },
    {
      "keyword": "atletico madrid",
      "score": 91
    }
  ]
}
