{
  "capturedAt": "2026-03-07T13:12:32.754Z",
  "geo": "KR",
  "source": "google",
  "items": [
    {
      "keyword": "แมนส์ฟิลด์ พบ อาร์เซนอล",
      "score": 100
    },
    {
      "keyword": "npb",
      "score": 99
    },
    {
      "keyword": "안우진",
      "score": 98
    },
    {
      "keyword": "오카모토 카즈마",
      "score": 97
    },
    {
      "keyword": "이대형",
      "score": 96
    },
    {
      "keyword": "로또1214",
      "score": 95
    },
    {
      "keyword": "mansfield town vs arsenal",
      "score": 94
    },
    {
      "keyword": "xsmb",
      "score": 93
    },
    {
      "keyword": "월드컵",
      "score": 92
    },
    {
      "keyword": "맨스필드 대 아스널",
      "score": 91
    }
  ]
}
