{
  "capturedAt": "2026-05-03T22:30:15.403Z",
  "geo": "KR",
  "source": "google",
  "items": [
    {
      "keyword": "가상자산",
      "score": 100
    },
    {
      "keyword": "롯데 자이언츠",
      "score": 99
    },
    {
      "keyword": "lg 트윈스",
      "score": 98
    },
    {
      "keyword": "선박",
      "score": 97
    },
    {
      "keyword": "김혜성",
      "score": 96
    },
    {
      "keyword": "포포투",
      "score": 95
    },
    {
      "keyword": "이란",
      "score": 94
    },
    {
      "keyword": "문세윤",
      "score": 93
    },
    {
      "keyword": "헌법",
      "score": 92
    },
    {
      "keyword": "음식",
      "score": 91
    }
  ]
}
