{
  "capturedAt": "2026-05-09T05:16:58.479Z",
  "geo": "US",
  "source": "google",
  "items": [
    {
      "keyword": "xinxin yao",
      "score": 100
    },
    {
      "keyword": "ca lottery",
      "score": 99
    },
    {
      "keyword": "shootout",
      "score": 98
    },
    {
      "keyword": "gloria trevi",
      "score": 97
    },
    {
      "keyword": "luigi mangione",
      "score": 96
    },
    {
      "keyword": "michael harris ii",
      "score": 95
    },
    {
      "keyword": "dodger score",
      "score": 94
    },
    {
      "keyword": "entergy",
      "score": 93
    },
    {
      "keyword": "braves",
      "score": 92
    },
    {
      "keyword": "brock stewart",
      "score": 91
    }
  ]
}
