{
  "capturedAt": "2026-03-27T23:27:26.710Z",
  "geo": "US",
  "source": "google",
  "items": [
    {
      "keyword": "bulls vs thunder",
      "score": 100
    },
    {
      "keyword": "rockets vs grizzlies",
      "score": 99
    },
    {
      "keyword": "jamal mashburn",
      "score": 98
    },
    {
      "keyword": "croatia",
      "score": 97
    },
    {
      "keyword": "u of m basketball",
      "score": 96
    },
    {
      "keyword": "chris sale",
      "score": 95
    },
    {
      "keyword": "duke university",
      "score": 94
    },
    {
      "keyword": "walt weiss",
      "score": 93
    },
    {
      "keyword": "james tolkan",
      "score": 92
    },
    {
      "keyword": "draftkings",
      "score": 91
    }
  ]
}
