{
  "capturedAt": "2026-02-22T13:56:32.955Z",
  "geo": "US",
  "source": "google",
  "items": [
    {
      "keyword": "milano cortina",
      "score": 100
    },
    {
      "keyword": "mark stone",
      "score": 99
    },
    {
      "keyword": "ovechkin",
      "score": 98
    },
    {
      "keyword": "atalanta - napoli",
      "score": 97
    },
    {
      "keyword": "nick suzuki",
      "score": 96
    },
    {
      "keyword": "brock nelson",
      "score": 95
    },
    {
      "keyword": "vincent trocheck",
      "score": 94
    },
    {
      "keyword": "medal count olympics 2026",
      "score": 93
    },
    {
      "keyword": "nascar race today",
      "score": 92
    },
    {
      "keyword": "lake placid olympics",
      "score": 91
    }
  ]
}
