{
  "capturedAt": "2026-02-15T17:17:27.149Z",
  "geo": "US",
  "source": "google",
  "items": [
    {
      "keyword": "macklin celebrini",
      "score": 100
    },
    {
      "keyword": "t20 world cup points table",
      "score": 99
    },
    {
      "keyword": "levante - valencia c. f.",
      "score": 98
    },
    {
      "keyword": "levante vs valencia",
      "score": 97
    },
    {
      "keyword": "netherlands",
      "score": 96
    },
    {
      "keyword": "torino vs bologna",
      "score": 95
    },
    {
      "keyword": "jake paul",
      "score": 94
    },
    {
      "keyword": "tpe country",
      "score": 93
    },
    {
      "keyword": "shaheen afridi",
      "score": 92
    },
    {
      "keyword": "utah basketball",
      "score": 91
    }
  ]
}
