{
  "capturedAt": "2026-01-16T11:39:07.771Z",
  "geo": "JP",
  "source": "google",
  "items": [
    {
      "keyword": "和田アキ子",
      "score": 100
    },
    {
      "keyword": "タモリ",
      "score": 99
    },
    {
      "keyword": "あいみょん",
      "score": 98
    },
    {
      "keyword": "imalu",
      "score": 97
    },
    {
      "keyword": "dazn",
      "score": 96
    },
    {
      "keyword": "tbs ドラマ",
      "score": 95
    },
    {
      "keyword": "せいや",
      "score": 94
    },
    {
      "keyword": "豊川悦司",
      "score": 93
    },
    {
      "keyword": "サンシャイン池崎",
      "score": 92
    },
    {
      "keyword": "島袋寛子",
      "score": 91
    }
  ]
}
