{
  "capturedAt": "2026-04-18T06:45:09.264Z",
  "geo": "US",
  "source": "google",
  "items": [
    {
      "keyword": "aj styles",
      "score": 100
    },
    {
      "keyword": "prince harry",
      "score": 99
    },
    {
      "keyword": "troy baker",
      "score": 98
    },
    {
      "keyword": "gwen stefani",
      "score": 97
    },
    {
      "keyword": "swae lee",
      "score": 96
    },
    {
      "keyword": "nick hogan",
      "score": 95
    },
    {
      "keyword": "disclosure",
      "score": 94
    },
    {
      "keyword": "joost klein",
      "score": 93
    },
    {
      "keyword": "ryan ward",
      "score": 92
    },
    {
      "keyword": "star wars movies",
      "score": 91
    }
  ]
}
