{
  "capturedAt": "2026-01-28T18:24:54.753Z",
  "geo": "US",
  "source": "google",
  "items": [
    {
      "keyword": "charles victor thompson",
      "score": 100
    },
    {
      "keyword": "polio",
      "score": 99
    },
    {
      "keyword": "breeze airways",
      "score": 98
    },
    {
      "keyword": "shirley raines",
      "score": 97
    },
    {
      "keyword": "al-ahli saudi vs al-ettifaq",
      "score": 96
    },
    {
      "keyword": "henry reagan",
      "score": 95
    },
    {
      "keyword": "patrick reed",
      "score": 94
    },
    {
      "keyword": "tammy duckworth",
      "score": 93
    },
    {
      "keyword": "rand paul",
      "score": 92
    },
    {
      "keyword": "michael dell",
      "score": 91
    }
  ]
}
