{
  "capturedAt": "2026-07-04T05:57:17.517Z",
  "geo": "JP",
  "source": "youtube",
  "items": [
    {
      "keyword": "EBiDAN(恵比寿学園男子部) 「Yes! 東京」 MUSIC VIDEO",
      "score": 7.376
    },
    {
      "keyword": "【マインクラフト】地下の強制労働施設で埋蔵金を探すことになりました【日常組】",
      "score": 6.762
    },
    {
      "keyword": "【予告2】劇場版『TOKYO MER～走る緊急救命室～CAPITAL CRISIS』《8月21日(金)公開》",
      "score": 6.755
    },
    {
      "keyword": "『劇場版 薬屋のひとりごと 亡妃の秘宝』予告｜2026年12月11日（金）公開",
      "score": 6.754
    },
    {
      "keyword": "チラチLOVE (from M!LK ARENA TOUR 2025-2026 \"SMILE POP!\")",
      "score": 6.635
    },
    {
      "keyword": "【Ado】Love me forever!（Official Audio）",
      "score": 6.618
    },
    {
      "keyword": "『崩壊：スターレイル』Ver.4.4「汽笛は轟く、帰寂のさなかに」予告番組",
      "score": 6.554
    },
    {
      "keyword": "【 パワプロ2026 】初めての栄冠ナイン!!どんだんず高校始動!!⚾【 猫又おかゆ/ホロライブ 】#パワプロケモミミリーグ",
      "score": 6.485
    },
    {
      "keyword": "【リズム天国ミラクルスターズ】全力リズム天国やるにぇええええええええええええ‼🔥【ホロライブ/さくらみこ】",
      "score": 6.44
    },
    {
      "keyword": "めっちゃカメレオンにMODを追加したら..",
      "score": 6.437
    },
    {
      "keyword": "二度と帰れない！？別世界に飛ばされてしまいました…【マイクラ】",
      "score": 6.432
    },
    {
      "keyword": "BE:FIRST / Missing -Behind The Scenes-",
      "score": 6.414
    },
    {
      "keyword": "LE SSERAFIM (르세라핌) 'BOOMPALA (feat. GURU RANDHAWA)' Official Film",
      "score": 6.391
    },
    {
      "keyword": "初期JPのアムネジアを超える当身なんて格ゲー界に存在しないと思っていたが、世界を知り戦慄を覚えるカワノ【スト6】",
      "score": 6.381
    },
    {
      "keyword": "海外で話題の超危険なVerity Modがやばすぎた【 マイクラ / マインクラフト 】",
      "score": 6.379
    },
    {
      "keyword": "いま、大いなる力が目覚める――🕷『スパイダーマン：ブランド・ニュー・デイ』＜60秒予告＞7月31日（金）日米同時公開！",
      "score": 6.335
    },
    {
      "keyword": "【特報】『劇場版 俺だけレベルアップな件 -Beyond the System-』制作決定",
      "score": 6.317
    },
    {
      "keyword": "【激闘】視聴者の構築バトル、遂に最終戦！『悪魔的構築』VS『最強ブイズ統一』で頂上決戦！！",
      "score": 6.276
    },
    {
      "keyword": "加藤純一のパワフルプロ野球2026-2027 栄冠ナインダイジェスト【2026/06/30,07/01-1】",
      "score": 6.179
    },
    {
      "keyword": "【デッドバイデイライト（DbD）】サイレントヒルｆから深水雛子登場！【弟者】",
      "score": 6.166
    }
  ]
}
